{
  "schema": 3,
  "sistema_activo": true,
  "modo_autorizacion": "abierto",
  "mensaje_global": "Sistema operativo.",
  "version_minima": "9.6.5",
  "intervalo_minutos": 1,
  "intervalo_segundos": 5,
  "tolerancia_sin_internet_horas": 24,
  "bloquear_sin_internet": false,
  "actualizado_en": "2026-07-21 17:07:13",
  "usuarios": [
    {
      "id": "USR-13936527-9281-4ea4-b4ae-e54349bd9733",
      "usuario": "alexpedro",
      "nombre": "alexander pedro",
      "rol": "administrador",
      "activo": true,
      "vence": "",
      "equipos": [],
      "password": {
        "algoritmo": "pbkdf2_sha256",
        "iteraciones": 600000,
        "salt": "LS0JfB7K8s5FlWD1T17vkw==",
        "hash": "tcowa8/DZ295z+wwrTMbLBmS8U+7DjgHnAR60inLh3I="
      },
      "actualizado_en": "2026-07-21 17:07:08"
    }
  ],
  "equipos_autorizados": [],
  "equipos_bloqueados": []
}
